{
  "stages": [
    {
      "type": "veil:blit",
      "shader": "astrocraft:stars",
      "in": "minecraft:main",
      "out": "post_stars"
    },
    {
      "type": "veil:blit",
      "shader": "astrocraft:planets",
      "in": "post_stars",
      "out": "post_planet"
    },
    {
      "type": "veil:blit",
      "shader": "astrocraft:atmosphere",
      "in": "post_planet",
      "out": "post_atmosphere"
    },
    {
      "type": "veil:blit",
      "shader": "astrocraft:fxaa",
      "in": "post_atmosphere",
      "out": "veil:post"
    }
  ],
  "framebuffers": {
    "post_stars": {
      "depth": true,
      "format": "RGBA8",
      "autoClear": false,
      "linear": true
    },
    "post_planet": {
      "depth": true,
      "format": "RGBA32F",
      "autoClear": false,
      "linear": true
    },
    "post_atmosphere": {
      "depth": true,
      "format": "RGBA8",
      "autoClear": false,
      "linear": true
    }
  }
}